dna_ibp/__init__.py
dna_ibp/__main__.py
dna_ibp/__version__.py
dna_ibp/cli.py
dna_ibp/facades/__init__.py
dna_ibp/facades/analyse_facade.py
dna_ibp/facades/cpx_facade.py
dna_ibp/facades/g4hunter_facade.py
dna_ibp/facades/g4killer_facade.py
dna_ibp/facades/p53_facade.py
dna_ibp/facades/rloop_facade.py
dna_ibp/facades/sequence_facade.py
dna_ibp/facades/tool_facade.py
dna_ibp/facades/zdna_facade.py
dna_ibp/help.py
dna_ibp/parsers/__init__.py
dna_ibp/parsers/cpx_parser.py
dna_ibp/parsers/g4hunter_parser.py
dna_ibp/parsers/g4killer_parser.py
dna_ibp/parsers/p53_parser.py
dna_ibp/parsers/rloop_parser.py
dna_ibp/parsers/sequence_parser.py
dna_ibp/parsers/zdna_parser.py
dna_ibp/utils.py
dna_ibp-1.2.0.dist-info/entry_points.txt
dna_ibp-1.2.0.dist-info/LICENSE
dna_ibp-1.2.0.dist-info/METADATA
dna_ibp-1.2.0.dist-info/WHEEL
dna_ibp-1.2.0.dist-info/RECORD
