Metadata-Version: 2.3
Name: dna-ibp
Version: 1.2.0
Summary: Command-line tool for DNA sequence analysis and processing
License: MIT
Keywords: bioinformatics,DNA,cli
Author: Kryštof Kotrys
Author-email: krystofkotrys@gmail.com
Requires-Python: >=3.10,<4.0
Classifier: License :: OSI Approved :: MIT License
Classifier: Programming Language :: Python :: 3
Classifier: Programming Language :: Python :: 3.10
Classifier: Programming Language :: Python :: 3.11
Classifier: Programming Language :: Python :: 3.12
Classifier: Programming Language :: Python :: 3.13
Requires-Dist: DNA_analyser_IBP (>=3.7.1)
Project-URL: Homepage, https://github.com/krystofkotrys/dna-ibp-cli
